phoenix4all/__init__.py
phoenix4all/downloader.py
phoenix4all/io.py
phoenix4all/log.py
phoenix4all/radiative.py
phoenix4all/taurex.py
phoenix4all/cache/hiresfits/hiresfit_cache.jsonz
phoenix4all/cache/svo/svo_dataset.jsonz
phoenix4all/net/__init__.py
phoenix4all/net/http.py
phoenix4all/sources/__init__.py
phoenix4all/sources/core.py
phoenix4all/sources/hiresfits.py
phoenix4all/sources/pollux.py
phoenix4all/sources/registry.py
phoenix4all/sources/svo.py
phoenix4all/sources/synphot.py
phoenix4all-0.0.4.dist-info/METADATA
phoenix4all-0.0.4.dist-info/WHEEL
phoenix4all-0.0.4.dist-info/entry_points.txt
phoenix4all-0.0.4.dist-info/licenses/LICENSE
phoenix4all-0.0.4.dist-info/RECORD
