Metadata-Version: 2.4
Name: phoenix4all
Version: 0.0.4
Summary: All in one library for loading and using phoenix spectra
Project-URL: Homepage, https://taurex-space.github.io/phoenix4all/
Project-URL: Repository, https://github.com/taurex-space/phoenix4all
Project-URL: Documentation, https://taurex-space.github.io/phoenix4all/
Author-email: Ahmed Al-Refaie <ahmed.al-refaie@ucl.ac.uk>
License-File: LICENSE
Keywords: python
Classifier: Intended Audience :: Developers
Classifier: Programming Language :: Python
Classifier: Programming Language :: Python :: 3
Classifier: Programming Language :: Python :: 3.10
Classifier: Programming Language :: Python :: 3.11
Classifier: Programming Language :: Python :: 3.12
Classifier: Programming Language :: Python :: 3.13
Classifier: Topic :: Software Development :: Libraries :: Python Modules
Requires-Python: <4.0,>=3.10
Requires-Dist: astropy>=6.1.7
Requires-Dist: beautifulsoup4>=4.14.2
Requires-Dist: click>=8.1.8
Requires-Dist: numpy>=1.26.4
Requires-Dist: pandas>=2.3.3
Requires-Dist: requests>=2.32.5
Requires-Dist: tqdm>=4.67.1
Provides-Extra: taurex
Requires-Dist: taurex; extra == 'taurex'
